motionblinds/__init__.py
motionblinds/async_motion_blinds.py
motionblinds/motion_blinds.py
motionblinds-0.6.30.dist-info/licenses/LICENSE
motionblinds-0.6.30.dist-info/METADATA
motionblinds-0.6.30.dist-info/WHEEL
motionblinds-0.6.30.dist-info/top_level.txt
motionblinds-0.6.30.dist-info/RECORD
